<clinical_study>
  <!-- This xml conforms to an XML Schema at:
    https://clinicaltrials.gov/ct2/html/images/info/public.xsd -->
  <required_header>
    <download_date>ClinicalTrials.gov processed this data on May 29, 2018</download_date>
    <link_text>Link to the current ClinicalTrials.gov record.</link_text>
    <url>https://clinicaltrials.gov/show/NCT01246830</url>
  </required_header>
  <id_info>
    <org_study_id>S52731</org_study_id>
    <nct_id>NCT01246830</nct_id>
  </id_info>
  <brief_title>The Use of 2D and 3D Imaging Modalities and Its Influence on Diagnosis and Treatment Planning in Orthodontics</brief_title>
  <official_title>The Use of 2D and 3D Imaging Modalities and Its Influence on Diagnosis and Treatment Planning in Orthodontics</official_title>
  <sponsors>
    <lead_sponsor>
      <agency>Universitaire Ziekenhuizen Leuven</agency>
      <agency_class>Other</agency_class>
    </lead_sponsor>
    <collaborator>
      <agency>Katholieke Universiteit Leuven</agency>
      <agency_class>Other</agency_class>
    </collaborator>
  </sponsors>
  <source>Universitaire Ziekenhuizen Leuven</source>
  <oversight_info>
    <has_dmc>No</has_dmc>
  </oversight_info>
  <brief_summary>
    <textblock>
      Research questions:

        1. Will the panoramic images derived from cone beam CT data give better diagnostic ability
           than conventional panoramic radiographs?

        2. Will 3D cephalometric analysis offer the orthodontists and surgeons better information
           for treatment planning?

        3. Will the 3D cephalometric analysis give more accurate treatment plan and better
           treatment outcome?

      General hypothesis and special aims

      Overall aims:

        -  To compare 2D versus 3D cephalometric analysis: treatment planning and therapeutic
           outcome.

        -  To determine the accuracy and diagnostic ability and usability of the 3D cephalometric
           analysis.

        -  To evaluate the diagnostic ability and usability of the panoramic image derived from
           cone beam CT data as compared to 2D panoramic images.

        -  To evaluate the value of the cone beam CT data in cephalometric analysing process for
           orthodontic and maxillofacial surgery treatment.

      Hypotheses:

        1. The availability of the 3D cephalometric analysis influences the orthodontic and
           maxillofacial treatment plan and decision, and might change the treatment outcome.

        2. Panoramic images derived from cone beam CT data may provide equal information for
           diagnosis as conventional panoramic images.

        3. Cone beam CT will be able to replace &quot;classic orthodontic imaging&quot; being more time and
           dose efficient and having a beneficial effect on treatment outcome.
    </textblock>
  </brief_summary>
  <overall_status>Completed</overall_status>
  <start_date>January 2012</start_date>
  <completion_date type="Actual">September 2014</completion_date>
  <primary_completion_date type="Actual">December 2013</primary_completion_date>
  <study_type>Observational</study_type>
  <has_expanded_access>No</has_expanded_access>
  <study_design_info>
    <observational_model>Case Control</observational_model>
    <time_perspective>Prospective</time_perspective>
  </study_design_info>
  <primary_outcome>
    <measure>Cephalometric analysis</measure>
    <time_frame>at treatment planning step and after 2 years of treatment</time_frame>
    <description>linear and angular cephalometric measurement</description>
  </primary_outcome>
  <secondary_outcome>
    <measure>outcome of orthodontic treatment</measure>
    <time_frame>after 2 years of treatment</time_frame>
  </secondary_outcome>
  <number_of_groups>2</number_of_groups>
  <enrollment type="Actual">32</enrollment>
  <condition>Orthodontics</condition>
  <condition>Malocclusion</condition>
  <condition>Impacted Tooth</condition>
  <condition>Cephalometry</condition>
  <condition>Cone-Beam Computed Tomography</condition>
  <condition>Panoramic Radiography</condition>
  <arm_group>
    <arm_group_label>3D cephalometric analysis</arm_group_label>
  </arm_group>
  <arm_group>
    <arm_group_label>2D cephalometric analysis</arm_group_label>
  </arm_group>
  <intervention>
    <intervention_type>Radiation</intervention_type>
    <intervention_name>Panoramic radiograph, Cephalometric radiograph</intervention_name>
    <description>2D images that are used for orthodontic treatment planning</description>
    <arm_group_label>2D cephalometric analysis</arm_group_label>
  </intervention>
  <intervention>
    <intervention_type>Radiation</intervention_type>
    <intervention_name>Cone-beam computed tomography (CBCT)</intervention_name>
    <description>CBCT data will be used in 3D cephalometric analysis softwares</description>
    <arm_group_label>3D cephalometric analysis</arm_group_label>
  </intervention>
  <eligibility>
    <study_pop>
      <textblock>
        Patients who are seeking orthodontic and maxillofacial surgery treatments at the University
        Hospital Leuven with the need of conventional panoramic radiographs, cephalometric
        radiographs and cone beam CT images.
      </textblock>
    </study_pop>
    <sampling_method>Non-Probability Sample</sampling_method>
    <criteria>
      <textblock>
        Inclusion Criteria:

          -  age 12-25 years old

          -  Patients with malocclusions

          -  Patients with jaw relation defect both with or without the need of orthognathic
             surgery

          -  Patients with maxillofacial defects: tumors and trauma

          -  Patients with eruption problems: embedded or impacted teeth which have to be removed

        Exclusion Criteria:

          -  Patients with congenital deformities

          -  Patients with systemic diseases that may effect the growth formation: growth factor
             defect and thyroid hormone defect.
      </textblock>
    </criteria>
    <gender>All</gender>
    <minimum_age>12 Years</minimum_age>
    <maximum_age>25 Years</maximum_age>
    <healthy_volunteers>No</healthy_volunteers>
  </eligibility>
  <location>
    <facility>
      <name>Katholieke Universiteit Leuven</name>
      <address>
        <city>Leuven</city>
        <zip>3000</zip>
        <country>Belgium</country>
      </address>
    </facility>
  </location>
  <location>
    <facility>
      <name>University Hospital Leuven</name>
      <address>
        <city>Leuven</city>
        <zip>3000</zip>
        <country>Belgium</country>
      </address>
    </facility>
  </location>
  <location_countries>
    <country>Belgium</country>
  </location_countries>
  <reference>
    <citation>Broadbent BH. A new x-ray technique and its application to orthodontia. Angle Orthodontist 1931;51: 115-150</citation>
  </reference>
  <reference>
    <citation>Swennen GR, Schutyser F, Barth EL, De Groeve P, De Mey A. A new method of 3-D cephalometry Part I: the anatomic Cartesian 3-D reference system. J Craniofac Surg. 2006 Mar;17(2):314-25.</citation>
    <PMID>16633181</PMID>
  </reference>
  <reference>
    <citation>Swennen GR, Schutyser F. Three-dimensional cephalometry: spiral multi-slice vs cone-beam computed tomography. Am J Orthod Dentofacial Orthop. 2006 Sep;130(3):410-6.</citation>
    <PMID>16979502</PMID>
  </reference>
  <reference>
    <citation>Olszewski R, Cosnard G, Macq B, Mahy P, Reychler H. 3D CT-based cephalometric analysis: 3D cephalometric theoretical concept and software. Neuroradiology. 2006 Nov;48(11):853-62. Epub 2006 Sep 29.</citation>
    <PMID>17009024</PMID>
  </reference>
  <reference>
    <citation>Scarfe WC, Farman AG. What is cone-beam CT and how does it work? Dent Clin North Am. 2008 Oct;52(4):707-30, v. doi: 10.1016/j.cden.2008.05.005.</citation>
    <PMID>18805225</PMID>
  </reference>
  <reference>
    <citation>Carter L, Farman AG, Geist J, Scarfe WC, Angelopoulos C, Nair MK, Hildebolt CF, Tyndall D, Shrout M; American Academy of Oral and Maxillofacial Radiology. American Academy of Oral and Maxillofacial Radiology executive opinion statement on performing and interpreting diagnostic cone beam computed tomography. Oral Surg Oral Med Oral Pathol Oral Radiol Endod. 2008 Oct;106(4):561-2. doi: 10.1016/j.tripleo.2008.07.007.</citation>
    <PMID>18928899</PMID>
  </reference>
  <reference>
    <citation>Hassan B, van der Stelt P, Sanderink G. Accuracy of three-dimensional measurements obtained from cone beam computed tomography surface-rendered images for cephalometric analysis: influence of patient scanning position. Eur J Orthod. 2009 Apr;31(2):129-34. doi: 10.1093/ejo/cjn088. Epub 2008 Dec 23.</citation>
    <PMID>19106265</PMID>
  </reference>
  <reference>
    <citation>Lou L, Lagravere MO, Compton S, Major PW, Flores-Mir C. Accuracy of measurements and reliability of landmark identification with computed tomography (CT) techniques in the maxillofacial area: a systematic review. Oral Surg Oral Med Oral Pathol Oral Radiol Endod. 2007 Sep;104(3):402-11. Epub 2006 Oct 27. Review.</citation>
    <PMID>17709072</PMID>
  </reference>
  <reference>
    <citation>de Oliveira AE, Cevidanes LH, Phillips C, Motta A, Burke B, Tyndall D. Observer reliability of three-dimensional cephalometric landmark identification on cone-beam computerized tomography. Oral Surg Oral Med Oral Pathol Oral Radiol Endod. 2009 Feb;107(2):256-65. doi: 10.1016/j.tripleo.2008.05.039. Epub 2008 Aug 20.</citation>
    <PMID>18718796</PMID>
  </reference>
  <reference>
    <citation>Periago DR, Scarfe WC, Moshiri M, Scheetz JP, Silveira AM, Farman AG. Linear accuracy and reliability of cone beam CT derived 3-dimensional images constructed using an orthodontic volumetric rendering program. Angle Orthod. 2008 May;78(3):387-95. doi: 10.2319/122106-52.1.</citation>
    <PMID>18416632</PMID>
  </reference>
  <reference>
    <citation>Brown AA, Scarfe WC, Scheetz JP, Silveira AM, Farman AG. Linear accuracy of cone beam CT derived 3D images. Angle Orthod. 2009 Jan;79(1):150-7. doi: 10.2319/122407-599.1.</citation>
    <PMID>19123719</PMID>
  </reference>
  <reference>
    <citation>Olszewski R, Tanesy O, Cosnard G, Zech F, Reychler H. Reproducibility of osseous landmarks used for computed tomography based three-dimensional cephalometric analyses. J Craniomaxillofac Surg. 2010 Apr;38(3):214-21. doi: 10.1016/j.jcms.2009.05.005. Epub 2009 Jul 1.</citation>
    <PMID>19574058</PMID>
  </reference>
  <reference>
    <citation>Proffit WR, Fields HW Jr., Sarver DM. Contemporary Orthodontics. 4th ed, Mosby Inc., Elsevier Science, Philadelphia, 2006.</citation>
  </reference>
  <reference>
    <citation>White SC, Pharoah MJ. The evolution and application of dental maxillofacial imaging modalities. Dent Clin North Am. 2008 Oct;52(4):689-705, v. doi: 10.1016/j.cden.2008.05.006.</citation>
    <PMID>18805224</PMID>
  </reference>
  <verification_date>September 2010</verification_date>
  <!-- For several months we've had both old and new date name tags                             -->
  <!-- Now, the old date names have been dropped.                                               -->
  <!-- The new date name replacements are:                                                      -->
  <!--     OLD (gone)                                        NEW (in use)                       -->
  <!--   lastchanged_date                         becomes   last_update_submitted               -->
  <!--   firstreceived_date                       becomes   study_first_submitted               -->
  <!--   firstreceived_results_date               becomes   results_first_submitted             -->
  <!--   firstreceived_results_disposition_date   becomes   disposition_first_submitted         -->
  <study_first_submitted>November 22, 2010</study_first_submitted>
  <study_first_submitted_qc>November 22, 2010</study_first_submitted_qc>
  <study_first_posted type="Estimate">November 23, 2010</study_first_posted>
  <last_update_submitted>December 2, 2014</last_update_submitted>
  <last_update_submitted_qc>December 2, 2014</last_update_submitted_qc>
  <last_update_posted type="Estimate">December 3, 2014</last_update_posted>
  <responsible_party>
    <responsible_party_type>Sponsor</responsible_party_type>
  </responsible_party>
  <condition_browse>
    <!-- CAUTION:  The following MeSH terms are assigned with an imperfect algorithm            -->
    <mesh_term>Malocclusion</mesh_term>
    <mesh_term>Tooth, Impacted</mesh_term>
  </condition_browse>
  <!-- Results have not yet been posted for this study                                          -->
</clinical_study>

